odoo/addons/barcodes_generator_abstract/README.rst
odoo/addons/barcodes_generator_abstract/__init__.py
odoo/addons/barcodes_generator_abstract/__manifest__.py
odoo/addons/barcodes_generator_abstract/demo/res_users.xml
odoo/addons/barcodes_generator_abstract/i18n/am.po
odoo/addons/barcodes_generator_abstract/i18n/barcodes_generator_abstract.pot
odoo/addons/barcodes_generator_abstract/i18n/ca.po
odoo/addons/barcodes_generator_abstract/i18n/de.po
odoo/addons/barcodes_generator_abstract/i18n/el_GR.po
odoo/addons/barcodes_generator_abstract/i18n/es.po
odoo/addons/barcodes_generator_abstract/i18n/fi.po
odoo/addons/barcodes_generator_abstract/i18n/fr.po
odoo/addons/barcodes_generator_abstract/i18n/gl.po
odoo/addons/barcodes_generator_abstract/i18n/hr.po
odoo/addons/barcodes_generator_abstract/i18n/hr_HR.po
odoo/addons/barcodes_generator_abstract/i18n/it.po
odoo/addons/barcodes_generator_abstract/i18n/nl.po
odoo/addons/barcodes_generator_abstract/i18n/nl_NL.po
odoo/addons/barcodes_generator_abstract/i18n/pt.po
odoo/addons/barcodes_generator_abstract/i18n/pt_BR.po
odoo/addons/barcodes_generator_abstract/i18n/pt_PT.po
odoo/addons/barcodes_generator_abstract/i18n/sl.po
odoo/addons/barcodes_generator_abstract/i18n/tr.po
odoo/addons/barcodes_generator_abstract/i18n/zh_CN.po
odoo/addons/barcodes_generator_abstract/models/__init__.py
odoo/addons/barcodes_generator_abstract/models/barcode_generate_mixin.py
odoo/addons/barcodes_generator_abstract/models/barcode_rule.py
odoo/addons/barcodes_generator_abstract/readme/CONFIGURE.rst
odoo/addons/barcodes_generator_abstract/readme/CONTRIBUTORS.rst
odoo/addons/barcodes_generator_abstract/readme/CREDITS.rst
odoo/addons/barcodes_generator_abstract/readme/DESCRIPTION.rst
odoo/addons/barcodes_generator_abstract/readme/INSTALL.rst
odoo/addons/barcodes_generator_abstract/readme/ROADMAP.rst
odoo/addons/barcodes_generator_abstract/readme/USAGE.rst
odoo/addons/barcodes_generator_abstract/security/res_groups.xml
odoo14_addon_barcodes_generator_abstract-14.0.1.0.4.dist-info/METADATA
odoo14_addon_barcodes_generator_abstract-14.0.1.0.4.dist-info/WHEEL
odoo14_addon_barcodes_generator_abstract-14.0.1.0.4.dist-info/top_level.txt
odoo14_addon_barcodes_generator_abstract-14.0.1.0.4.dist-info/RECORD
